[
  {
    "ContainingType": "WebSastreria.Controllers.AuthController",
    "Method": "Login",
    "RelativePath": "api/Auth/login",
    "HttpMethod": "POST",
    "IsController": true,
    "Order": 0,
    "Parameters": [
      {
        "Name": "request",
        "Type": "sastreria_domain.RequestResponse.LoginRequest",
        "IsRequired": true
      }
    ],
    "ReturnTypes": []
  },
  {
    "ContainingType": "WebSastreria.Controllers.CategoriaController",
    "Method": "GetAll",
    "RelativePath": "api/Categoria",
    "HttpMethod": "GET",
    "IsController": true,
    "Order": 0,
    "Parameters": [],
    "ReturnTypes": [
      {
        "Type": "System.Collections.Generic.List\u00601[[WebSastreria.models.CategoriaResponse, sastreria_domain, Version=1.0.0.0, Culture=neutral, PublicKeyToken=null]]",
        "MediaTypes": [
          "text/plain",
          "application/json",
          "text/json"
        ],
        "StatusCode": 200
      }
    ]
  },
  {
    "ContainingType": "WebSastreria.Controllers.CategoriaController",
    "Method": "Create",
    "RelativePath": "api/Categoria",
    "HttpMethod": "POST",
    "IsController": true,
    "Order": 0,
    "Parameters": [
      {
        "Name": "request",
        "Type": "WebSastreria.models.CategoriaRequest",
        "IsRequired": true
      }
    ],
    "ReturnTypes": []
  },
  {
    "ContainingType": "WebSastreria.Controllers.CategoriaController",
    "Method": "GetById",
    "RelativePath": "api/Categoria/{id}",
    "HttpMethod": "GET",
    "IsController": true,
    "Order": 0,
    "Parameters": [
      {
        "Name": "id",
        "Type": "System.Int32",
        "IsRequired": true
      }
    ],
    "ReturnTypes": [
      {
        "Type": "WebSastreria.models.CategoriaResponse",
        "MediaTypes": [
          "text/plain",
          "application/json",
          "text/json"
        ],
        "StatusCode": 200
      }
    ]
  },
  {
    "ContainingType": "WebSastreria.Controllers.CategoriaController",
    "Method": "Update",
    "RelativePath": "api/Categoria/{id}",
    "HttpMethod": "PUT",
    "IsController": true,
    "Order": 0,
    "Parameters": [
      {
        "Name": "id",
        "Type": "System.Int32",
        "IsRequired": true
      },
      {
        "Name": "request",
        "Type": "WebSastreria.models.CategoriaRequest",
        "IsRequired": true
      }
    ],
    "ReturnTypes": []
  },
  {
    "ContainingType": "WebSastreria.Controllers.CategoriaController",
    "Method": "Delete",
    "RelativePath": "api/Categoria/{id}",
    "HttpMethod": "DELETE",
    "IsController": true,
    "Order": 0,
    "Parameters": [
      {
        "Name": "id",
        "Type": "System.Int32",
        "IsRequired": true
      }
    ],
    "ReturnTypes": []
  },
  {
    "ContainingType": "WebSastreria.Controllers.CategoriaController",
    "Method": "GetCategoriasConModelos",
    "RelativePath": "api/Categoria/con-modelos",
    "HttpMethod": "GET",
    "IsController": true,
    "Order": 0,
    "Parameters": [],
    "ReturnTypes": []
  },
  {
    "ContainingType": "WebSastreria.Controllers.CitaController",
    "Method": "GetAll",
    "RelativePath": "api/Cita",
    "HttpMethod": "GET",
    "IsController": true,
    "Order": 0,
    "Parameters": [],
    "ReturnTypes": []
  },
  {
    "ContainingType": "WebSastreria.Controllers.CitaController",
    "Method": "Create",
    "RelativePath": "api/Cita",
    "HttpMethod": "POST",
    "IsController": true,
    "Order": 0,
    "Parameters": [
      {
        "Name": "citaDomain",
        "Type": "sastreria_domain.entities.CitaDomain",
        "IsRequired": true
      }
    ],
    "ReturnTypes": []
  },
  {
    "ContainingType": "WebSastreria.Controllers.CitaController",
    "Method": "GetById",
    "RelativePath": "api/Cita/{id}",
    "HttpMethod": "GET",
    "IsController": true,
    "Order": 0,
    "Parameters": [
      {
        "Name": "id",
        "Type": "System.Int32",
        "IsRequired": true
      }
    ],
    "ReturnTypes": []
  },
  {
    "ContainingType": "WebSastreria.Controllers.CitaController",
    "Method": "Update",
    "RelativePath": "api/Cita/{id}",
    "HttpMethod": "PUT",
    "IsController": true,
    "Order": 0,
    "Parameters": [
      {
        "Name": "id",
        "Type": "System.Int32",
        "IsRequired": true
      },
      {
        "Name": "citaDomain",
        "Type": "sastreria_domain.entities.CitaDomain",
        "IsRequired": true
      }
    ],
    "ReturnTypes": []
  },
  {
    "ContainingType": "WebSastreria.Controllers.CitaController",
    "Method": "Delete",
    "RelativePath": "api/Cita/{id}",
    "HttpMethod": "DELETE",
    "IsController": true,
    "Order": 0,
    "Parameters": [
      {
        "Name": "id",
        "Type": "System.Int32",
        "IsRequired": true
      }
    ],
    "ReturnTypes": []
  },
  {
    "ContainingType": "WebSastreria.Controllers.CitaController",
    "Method": "GetImagenesPorCita",
    "RelativePath": "api/Cita/{idCita}/imagenes",
    "HttpMethod": "GET",
    "IsController": true,
    "Order": 0,
    "Parameters": [
      {
        "Name": "idCita",
        "Type": "System.Int32",
        "IsRequired": true
      }
    ],
    "ReturnTypes": []
  },
  {
    "ContainingType": "WebSastreria.Controllers.CitaController",
    "Method": "AgregarImagenes",
    "RelativePath": "api/Cita/{idCita}/imagenes",
    "HttpMethod": "POST",
    "IsController": true,
    "Order": 0,
    "Parameters": [
      {
        "Name": "idCita",
        "Type": "System.Int32",
        "IsRequired": true
      },
      {
        "Name": "urls",
        "Type": "System.Collections.Generic.List\u00601[[System.String, System.Private.CoreLib, Version=8.0.0.0, Culture=neutral, PublicKeyToken=7cec85d7bea7798e]]",
        "IsRequired": true
      }
    ],
    "ReturnTypes": []
  },
  {
    "ContainingType": "WebSastreria.Controllers.ClienteController",
    "Method": "GetAll",
    "RelativePath": "api/Cliente",
    "HttpMethod": "GET",
    "IsController": true,
    "Order": 0,
    "Parameters": [],
    "ReturnTypes": []
  },
  {
    "ContainingType": "WebSastreria.Controllers.ClienteController",
    "Method": "Create",
    "RelativePath": "api/Cliente",
    "HttpMethod": "POST",
    "IsController": true,
    "Order": 0,
    "Parameters": [
      {
        "Name": "clienteDto",
        "Type": "WebSastreria.Dtos.ClienteCreateDto",
        "IsRequired": true
      }
    ],
    "ReturnTypes": []
  },
  {
    "ContainingType": "WebSastreria.Controllers.ClienteController",
    "Method": "GetById",
    "RelativePath": "api/Cliente/{id}",
    "HttpMethod": "GET",
    "IsController": true,
    "Order": 0,
    "Parameters": [
      {
        "Name": "id",
        "Type": "System.Int32",
        "IsRequired": true
      }
    ],
    "ReturnTypes": []
  },
  {
    "ContainingType": "WebSastreria.Controllers.ClienteController",
    "Method": "Update",
    "RelativePath": "api/Cliente/{id}",
    "HttpMethod": "PUT",
    "IsController": true,
    "Order": 0,
    "Parameters": [
      {
        "Name": "id",
        "Type": "System.Int32",
        "IsRequired": true
      },
      {
        "Name": "clienteDomain",
        "Type": "sastreria_domain.entities.ClienteDomain",
        "IsRequired": true
      }
    ],
    "ReturnTypes": []
  },
  {
    "ContainingType": "WebSastreria.Controllers.ClienteController",
    "Method": "Delete",
    "RelativePath": "api/Cliente/{id}",
    "HttpMethod": "DELETE",
    "IsController": true,
    "Order": 0,
    "Parameters": [
      {
        "Name": "id",
        "Type": "System.Int32",
        "IsRequired": true
      }
    ],
    "ReturnTypes": []
  },
  {
    "ContainingType": "WebSastreria.Controllers.ClienteController",
    "Method": "BuscarPorDni",
    "RelativePath": "api/Cliente/buscar-por-dni/dni/{dni}",
    "HttpMethod": "GET",
    "IsController": true,
    "Order": 0,
    "Parameters": [
      {
        "Name": "dni",
        "Type": "System.String",
        "IsRequired": true
      }
    ],
    "ReturnTypes": []
  },
  {
    "ContainingType": "WebSastreria.Controllers.ClienteController",
    "Method": "GetByDni",
    "RelativePath": "api/Cliente/por-dni/{dni}",
    "HttpMethod": "GET",
    "IsController": true,
    "Order": 0,
    "Parameters": [
      {
        "Name": "dni",
        "Type": "System.String",
        "IsRequired": true
      }
    ],
    "ReturnTypes": []
  },
  {
    "ContainingType": "WebSastreria.Controllers.DatoSastreriaController",
    "Method": "GetAll",
    "RelativePath": "api/DatoSastreria",
    "HttpMethod": "GET",
    "IsController": true,
    "Order": 0,
    "Parameters": [],
    "ReturnTypes": []
  },
  {
    "ContainingType": "WebSastreria.Controllers.DatoSastreriaController",
    "Method": "Create",
    "RelativePath": "api/DatoSastreria",
    "HttpMethod": "POST",
    "IsController": true,
    "Order": 0,
    "Parameters": [
      {
        "Name": "dto",
        "Type": "WebSastreria.Dtos.DatoSastreriaDto",
        "IsRequired": true
      }
    ],
    "ReturnTypes": []
  },
  {
    "ContainingType": "WebSastreria.Controllers.DatoSastreriaController",
    "Method": "GetById",
    "RelativePath": "api/DatoSastreria/{id}",
    "HttpMethod": "GET",
    "IsController": true,
    "Order": 0,
    "Parameters": [
      {
        "Name": "id",
        "Type": "System.Int32",
        "IsRequired": true
      }
    ],
    "ReturnTypes": []
  },
  {
    "ContainingType": "WebSastreria.Controllers.DatoSastreriaController",
    "Method": "Update",
    "RelativePath": "api/DatoSastreria/{id}",
    "HttpMethod": "PUT",
    "IsController": true,
    "Order": 0,
    "Parameters": [
      {
        "Name": "id",
        "Type": "System.Int32",
        "IsRequired": true
      },
      {
        "Name": "dto",
        "Type": "WebSastreria.Dtos.DatoSastreriaDto",
        "IsRequired": true
      }
    ],
    "ReturnTypes": []
  },
  {
    "ContainingType": "WebSastreria.Controllers.DatoSastreriaController",
    "Method": "Delete",
    "RelativePath": "api/DatoSastreria/{id}",
    "HttpMethod": "DELETE",
    "IsController": true,
    "Order": 0,
    "Parameters": [
      {
        "Name": "id",
        "Type": "System.Int32",
        "IsRequired": true
      }
    ],
    "ReturnTypes": []
  },
  {
    "ContainingType": "WebSastreria.Controllers.EstadoController",
    "Method": "GetAll",
    "RelativePath": "api/Estado",
    "HttpMethod": "GET",
    "IsController": true,
    "Order": 0,
    "Parameters": [],
    "ReturnTypes": []
  },
  {
    "ContainingType": "WebSastreria.Controllers.EstadoController",
    "Method": "Create",
    "RelativePath": "api/Estado",
    "HttpMethod": "POST",
    "IsController": true,
    "Order": 0,
    "Parameters": [
      {
        "Name": "dto",
        "Type": "WebSastreria.Dtos.EstadoDto",
        "IsRequired": true
      }
    ],
    "ReturnTypes": []
  },
  {
    "ContainingType": "WebSastreria.Controllers.EstadoController",
    "Method": "GetById",
    "RelativePath": "api/Estado/{id}",
    "HttpMethod": "GET",
    "IsController": true,
    "Order": 0,
    "Parameters": [
      {
        "Name": "id",
        "Type": "System.Int32",
        "IsRequired": true
      }
    ],
    "ReturnTypes": []
  },
  {
    "ContainingType": "WebSastreria.Controllers.EstadoController",
    "Method": "Update",
    "RelativePath": "api/Estado/{id}",
    "HttpMethod": "PUT",
    "IsController": true,
    "Order": 0,
    "Parameters": [
      {
        "Name": "id",
        "Type": "System.Int32",
        "IsRequired": true
      },
      {
        "Name": "dto",
        "Type": "WebSastreria.Dtos.EstadoDto",
        "IsRequired": true
      }
    ],
    "ReturnTypes": []
  },
  {
    "ContainingType": "WebSastreria.Controllers.EstadoController",
    "Method": "Delete",
    "RelativePath": "api/Estado/{id}",
    "HttpMethod": "DELETE",
    "IsController": true,
    "Order": 0,
    "Parameters": [
      {
        "Name": "id",
        "Type": "System.Int32",
        "IsRequired": true
      }
    ],
    "ReturnTypes": []
  },
  {
    "ContainingType": "WebSastreria.Controllers.HorarioController",
    "Method": "GetAll",
    "RelativePath": "api/Horario",
    "HttpMethod": "GET",
    "IsController": true,
    "Order": 0,
    "Parameters": [],
    "ReturnTypes": []
  },
  {
    "ContainingType": "WebSastreria.Controllers.HorarioController",
    "Method": "Create",
    "RelativePath": "api/Horario",
    "HttpMethod": "POST",
    "IsController": true,
    "Order": 0,
    "Parameters": [
      {
        "Name": "horarioDto",
        "Type": "WebSastreria.Dtos.HorarioDto",
        "IsRequired": true
      }
    ],
    "ReturnTypes": []
  },
  {
    "ContainingType": "WebSastreria.Controllers.HorarioController",
    "Method": "GetById",
    "RelativePath": "api/Horario/{id}",
    "HttpMethod": "GET",
    "IsController": true,
    "Order": 0,
    "Parameters": [
      {
        "Name": "id",
        "Type": "System.Int32",
        "IsRequired": true
      }
    ],
    "ReturnTypes": []
  },
  {
    "ContainingType": "WebSastreria.Controllers.HorarioController",
    "Method": "Update",
    "RelativePath": "api/Horario/{id}",
    "HttpMethod": "PUT",
    "IsController": true,
    "Order": 0,
    "Parameters": [
      {
        "Name": "id",
        "Type": "System.Int32",
        "IsRequired": true
      },
      {
        "Name": "horarioDto",
        "Type": "WebSastreria.Dtos.HorarioDto",
        "IsRequired": true
      }
    ],
    "ReturnTypes": []
  },
  {
    "ContainingType": "WebSastreria.Controllers.HorarioController",
    "Method": "Delete",
    "RelativePath": "api/Horario/{id}",
    "HttpMethod": "DELETE",
    "IsController": true,
    "Order": 0,
    "Parameters": [
      {
        "Name": "id",
        "Type": "System.Int32",
        "IsRequired": true
      }
    ],
    "ReturnTypes": []
  },
  {
    "ContainingType": "WebSastreria.Controllers.ModeloController",
    "Method": "GetAll",
    "RelativePath": "api/Modelo",
    "HttpMethod": "GET",
    "IsController": true,
    "Order": 0,
    "Parameters": [],
    "ReturnTypes": [
      {
        "Type": "System.Collections.Generic.List\u00601[[sastreria_domain.RequestResponse.ModeloResponse, sastreria_domain, Version=1.0.0.0, Culture=neutral, PublicKeyToken=null]]",
        "MediaTypes": [
          "text/plain",
          "application/json",
          "text/json"
        ],
        "StatusCode": 200
      }
    ]
  },
  {
    "ContainingType": "WebSastreria.Controllers.ModeloController",
    "Method": "Create",
    "RelativePath": "api/Modelo",
    "HttpMethod": "POST",
    "IsController": true,
    "Order": 0,
    "Parameters": [
      {
        "Name": "request",
        "Type": "sastreria_domain.RequestResponse.ModeloRequest",
        "IsRequired": true
      }
    ],
    "ReturnTypes": [
      {
        "Type": "sastreria_domain.RequestResponse.ModeloResponse",
        "MediaTypes": [
          "text/plain",
          "application/json",
          "text/json"
        ],
        "StatusCode": 200
      }
    ]
  },
  {
    "ContainingType": "WebSastreria.Controllers.ModeloController",
    "Method": "GetById",
    "RelativePath": "api/Modelo/{id}",
    "HttpMethod": "GET",
    "IsController": true,
    "Order": 0,
    "Parameters": [
      {
        "Name": "id",
        "Type": "System.Int32",
        "IsRequired": true
      }
    ],
    "ReturnTypes": [
      {
        "Type": "sastreria_domain.RequestResponse.ModeloResponse",
        "MediaTypes": [
          "text/plain",
          "application/json",
          "text/json"
        ],
        "StatusCode": 200
      }
    ]
  },
  {
    "ContainingType": "WebSastreria.Controllers.ModeloController",
    "Method": "Update",
    "RelativePath": "api/Modelo/{id}",
    "HttpMethod": "PUT",
    "IsController": true,
    "Order": 0,
    "Parameters": [
      {
        "Name": "id",
        "Type": "System.Int32",
        "IsRequired": true
      },
      {
        "Name": "request",
        "Type": "sastreria_domain.RequestResponse.ModeloRequest",
        "IsRequired": true
      }
    ],
    "ReturnTypes": []
  },
  {
    "ContainingType": "WebSastreria.Controllers.ModeloController",
    "Method": "Delete",
    "RelativePath": "api/Modelo/{id}",
    "HttpMethod": "DELETE",
    "IsController": true,
    "Order": 0,
    "Parameters": [
      {
        "Name": "id",
        "Type": "System.Int32",
        "IsRequired": true
      }
    ],
    "ReturnTypes": []
  },
  {
    "ContainingType": "WebSastreria.Controllers.ModeloController",
    "Method": "GetByCategoria",
    "RelativePath": "api/Modelo/categorias",
    "HttpMethod": "GET",
    "IsController": true,
    "Order": 0,
    "Parameters": [],
    "ReturnTypes": []
  },
  {
    "ContainingType": "WebSastreria.Controllers.PedidoController",
    "Method": "GetAll",
    "RelativePath": "api/Pedido",
    "HttpMethod": "GET",
    "IsController": true,
    "Order": 0,
    "Parameters": [],
    "ReturnTypes": []
  },
  {
    "ContainingType": "WebSastreria.Controllers.PedidoController",
    "Method": "Create",
    "RelativePath": "api/Pedido",
    "HttpMethod": "POST",
    "IsController": true,
    "Order": 0,
    "Parameters": [
      {
        "Name": "pedidoDomain",
        "Type": "sastreria_domain.entities.PedidoDomain",
        "IsRequired": true
      }
    ],
    "ReturnTypes": []
  },
  {
    "ContainingType": "WebSastreria.Controllers.PedidoController",
    "Method": "GetById",
    "RelativePath": "api/Pedido/{id}",
    "HttpMethod": "GET",
    "IsController": true,
    "Order": 0,
    "Parameters": [
      {
        "Name": "id",
        "Type": "System.Int32",
        "IsRequired": true
      }
    ],
    "ReturnTypes": []
  },
  {
    "ContainingType": "WebSastreria.Controllers.PedidoController",
    "Method": "Update",
    "RelativePath": "api/Pedido/{id}",
    "HttpMethod": "PUT",
    "IsController": true,
    "Order": 0,
    "Parameters": [
      {
        "Name": "id",
        "Type": "System.Int32",
        "IsRequired": true
      },
      {
        "Name": "pedidoDomain",
        "Type": "sastreria_domain.entities.PedidoDomain",
        "IsRequired": true
      }
    ],
    "ReturnTypes": []
  },
  {
    "ContainingType": "WebSastreria.Controllers.PedidoController",
    "Method": "Delete",
    "RelativePath": "api/Pedido/{id}",
    "HttpMethod": "DELETE",
    "IsController": true,
    "Order": 0,
    "Parameters": [
      {
        "Name": "id",
        "Type": "System.Int32",
        "IsRequired": true
      }
    ],
    "ReturnTypes": []
  },
  {
    "ContainingType": "WebSastreria.Controllers.SastreController",
    "Method": "GetAll",
    "RelativePath": "api/Sastre",
    "HttpMethod": "GET",
    "IsController": true,
    "Order": 0,
    "Parameters": [],
    "ReturnTypes": []
  },
  {
    "ContainingType": "WebSastreria.Controllers.SastreController",
    "Method": "Create",
    "RelativePath": "api/Sastre",
    "HttpMethod": "POST",
    "IsController": true,
    "Order": 0,
    "Parameters": [
      {
        "Name": "dto",
        "Type": "WebSastreria.Dtos.SastreDto",
        "IsRequired": true
      }
    ],
    "ReturnTypes": []
  },
  {
    "ContainingType": "WebSastreria.Controllers.SastreController",
    "Method": "GetById",
    "RelativePath": "api/Sastre/{id}",
    "HttpMethod": "GET",
    "IsController": true,
    "Order": 0,
    "Parameters": [
      {
        "Name": "id",
        "Type": "System.Int32",
        "IsRequired": true
      }
    ],
    "ReturnTypes": []
  },
  {
    "ContainingType": "WebSastreria.Controllers.SastreController",
    "Method": "Update",
    "RelativePath": "api/Sastre/{id}",
    "HttpMethod": "PUT",
    "IsController": true,
    "Order": 0,
    "Parameters": [
      {
        "Name": "id",
        "Type": "System.Int32",
        "IsRequired": true
      },
      {
        "Name": "dto",
        "Type": "WebSastreria.Dtos.SastreDto",
        "IsRequired": true
      }
    ],
    "ReturnTypes": []
  },
  {
    "ContainingType": "WebSastreria.Controllers.SastreController",
    "Method": "Delete",
    "RelativePath": "api/Sastre/{id}",
    "HttpMethod": "DELETE",
    "IsController": true,
    "Order": 0,
    "Parameters": [
      {
        "Name": "id",
        "Type": "System.Int32",
        "IsRequired": true
      }
    ],
    "ReturnTypes": []
  },
  {
    "ContainingType": "WebSastreria.Controllers.TipoDocumentoController",
    "Method": "GetAll",
    "RelativePath": "api/TipoDocumento",
    "HttpMethod": "GET",
    "IsController": true,
    "Order": 0,
    "Parameters": [],
    "ReturnTypes": []
  },
  {
    "ContainingType": "WebSastreria.Controllers.TipoDocumentoController",
    "Method": "Create",
    "RelativePath": "api/TipoDocumento",
    "HttpMethod": "POST",
    "IsController": true,
    "Order": 0,
    "Parameters": [
      {
        "Name": "tipoDocumentoDomain",
        "Type": "sastreria_domain.entities.TipoDocumentoDomain",
        "IsRequired": true
      }
    ],
    "ReturnTypes": []
  },
  {
    "ContainingType": "WebSastreria.Controllers.TipoDocumentoController",
    "Method": "GetById",
    "RelativePath": "api/TipoDocumento/{id}",
    "HttpMethod": "GET",
    "IsController": true,
    "Order": 0,
    "Parameters": [
      {
        "Name": "id",
        "Type": "System.Int32",
        "IsRequired": true
      }
    ],
    "ReturnTypes": []
  },
  {
    "ContainingType": "WebSastreria.Controllers.TipoDocumentoController",
    "Method": "Update",
    "RelativePath": "api/TipoDocumento/{id}",
    "HttpMethod": "PUT",
    "IsController": true,
    "Order": 0,
    "Parameters": [
      {
        "Name": "id",
        "Type": "System.Int32",
        "IsRequired": true
      },
      {
        "Name": "tipoDocumentoDomain",
        "Type": "sastreria_domain.entities.TipoDocumentoDomain",
        "IsRequired": true
      }
    ],
    "ReturnTypes": []
  },
  {
    "ContainingType": "WebSastreria.Controllers.TipoDocumentoController",
    "Method": "Delete",
    "RelativePath": "api/TipoDocumento/{id}",
    "HttpMethod": "DELETE",
    "IsController": true,
    "Order": 0,
    "Parameters": [
      {
        "Name": "id",
        "Type": "System.Int32",
        "IsRequired": true
      }
    ],
    "ReturnTypes": []
  }
]